panopticon/__init__.py
panopticon/__main__.py
panopticon/post.py
panopticon/probe.py
panopticon/trace.py
panopticon/tracer.py
panopticon/version.py
tests/__init__.py
tests/test_async_probe.py
tests/test_init.py
tests/test_post.py
tests/test_probe.py
tests/test_tracer.py
tests/utils.py
panopticon-0.0.4.dist-info/LICENSE
panopticon-0.0.4.dist-info/METADATA
panopticon-0.0.4.dist-info/WHEEL
panopticon-0.0.4.dist-info/top_level.txt
panopticon-0.0.4.dist-info/RECORD
