Metadata-Version: 2.1
Name: panopticon
Version: 0.0.4
Summary: A python tracer
Home-page: https://github.com/kunalb/panopticon
Author: Kunal Bhalla
Author-email: bhalla.kunal@gmail.com
License: UNKNOWN
Platform: UNKNOWN
Classifier: Programming Language :: Python :: 3
Classifier: License :: OSI Approved :: MIT License
Classifier: Operating System :: OS Independent
Classifier: Development Status :: 3 - Alpha
Requires-Python: >=3.7
